aiffel7/__init__.py
aiffel7/get_tf_api_info.py
aiffel7/history_graph.py
aiffel7/history_logger.py
aiffel7/historylogger.py
aiffel7/learning_rate.py
aiffel7/lr_schedule.py
aiffel7/my_module.py
aiffel7/version.py
tripleyoung/__init__.py
tripleyoung/my_module.py
aiffel7-0.6.11.dist-info/LICENSE
aiffel7-0.6.11.dist-info/METADATA
aiffel7-0.6.11.dist-info/WHEEL
aiffel7-0.6.11.dist-info/top_level.txt
aiffel7-0.6.11.dist-info/RECORD
