Metadata-Version: 2.1
Name: aiffel7
Version: 0.6.11
Summary: A simple Python library
Home-page: https://github.com/dudnjsckrgo/aiffel7_library
Author: aiffel7_그루
Author-email: your.email@example.com
License: LICENSE
License-File: LICENSE
Requires-Dist: beautifulsoup4
Requires-Dist: requests
Requires-Dist: matplotlib
Requires-Dist: tensorflow >=2.0
